circFL_refine/__init__.py
circFL_refine/circFL_refine_main.py
circFL_refine/construct.py
circFL_refine/correct.py
circFL_refine/evaluate.py
circFL_refine/genericFun.py
circFL_refine/train.py
circFL_refine/version.py
circFL_refine-1.0.0.dist-info/METADATA
circFL_refine-1.0.0.dist-info/WHEEL
circFL_refine-1.0.0.dist-info/entry_points.txt
circFL_refine-1.0.0.dist-info/top_level.txt
circFL_refine-1.0.0.dist-info/RECORD
