Metadata-Version: 2.1
Name: circFL-refine
Version: 1.0.0
Summary: circFL-refine: a tool for full-length circRNA isoform construction based on convolutional neural network
Home-page: https://github.com/yangence/circFL-refine
Author: Zelin Liu
Author-email: zlliu@bjmu.edu.cn
License: GPL3
Keywords: circular RNAs
Platform: UNKNOWN
Requires-Python: >=3
Requires-Dist: pandas (>=0.25.2)
Requires-Dist: numpy (>=1.17.5)
Requires-Dist: docopt (>=0.6.2)
Requires-Dist: scikit-learn (>=0.24.2)
Requires-Dist: pyfasta (>=0.5.2)
Requires-Dist: torch (>=1.7.1)
